dedup/__init__.py
dedup/alignment.py
dedup/contig.py
dedup/dedup.py
dedup/kmer_spectrum.py
dedup/kmer_utilities.py
dedup/logging_config.py
dedup/test/__init__.py
dedup/test/test_alignment.py
dedup/test/test_contig.py
dedup_assembly-1.0.dist-info/LICENSE
dedup_assembly-1.0.dist-info/METADATA
dedup_assembly-1.0.dist-info/WHEEL
dedup_assembly-1.0.dist-info/entry_points.txt
dedup_assembly-1.0.dist-info/top_level.txt
dedup_assembly-1.0.dist-info/RECORD
