Metadata-Version: 2.1
Name: dedup-assembly
Version: 1.0
Summary: Deduplicate haplotigs from complex diploid genomes
Home-page: https://github.com/doenjon/dedup
Author: Jon Doenier
Author-email: doenierjon@gmail.com
License: MIT license
Classifier: Programming Language :: Python :: 3
Classifier: License :: OSI Approved :: MIT License
Classifier: Operating System :: OS Independent
Requires-Python: >=3.8
License-File: LICENSE
Requires-Dist: numpy
Requires-Dist: pandas
Requires-Dist: plotly
Requires-Dist: scipy
Requires-Dist: seaborn
Requires-Dist: matplotlib
Requires-Dist: biopython
Requires-Dist: datasketch
Requires-Dist: networkx
